{
    "genn": {
        "repeat": 10,
        "neuron_type": "IF_cond_exp",
        "neuron_params": {
            "e_rev_E": 0,
            "e_rev_I": -90,
            "v_rest": -70,
            "v_reset": -80,
            "v_thresh": -60,
            "tau_syn_E": 2,
            "tau_syn_I": 2,
            "tau_refrac": 2,
            "tau_m": 1,
            "cm": 0.2
        },
        "num_neurons_pop": 10,
        "num_source_neurons": 10,
        "num_inhibitory_neurons": 10,
        "weight_inp": 0.011,
        "weight_self": 0.0086,
        "weight_lat_inh": -0.009,
        "weight_lat_exc": 0.005,
        "prob_inp": 0.8,
        "prob_self": 0.8,
        "prob_lat_exc": 0.8,
        "firing_rate": 80,
        "delay": 1.0,
        "setup": {
            "timestep": 1.0
        }
    },
    "nest": {
        "repeat": 10,
        "neuron_type": "IF_cond_exp",
        "neuron_params": {
            "e_rev_E": 0,
            "v_rest": -70,
            "v_reset": -80,
            "v_thresh": -60,
            "tau_syn_E": 2,
            "tau_refrac": 1,
            "tau_m": 1,
            "cm": 0.2
        },
        "num_neurons_pop": 10,
        "num_source_neurons": 10,
        "num_inhibitory_neurons": 10,
        "weight_inp": 0.01,
        "weight_self": 0.009,
        "weight_lat_inh": -0.005,
        "weight_lat_exc": 0.005,
        "prob_inp": 0.8,
        "prob_self": 0.8,
        "prob_lat_exc": 0.8,
        "firing_rate": 80
    },
    "spinnaker": {
        "repeat": 10,
        "neuron_type": "IF_cond_exp",
        "neuron_params": {
            "e_rev_E": 0,
            "e_rev_I": -90,
            "v_rest": -70,
            "v_reset": -80,
            "v_thresh": -60,
            "tau_syn_E": 2,
            "tau_syn_I": 2,
            "tau_refrac": 2,
            "tau_m": 1,
            "cm": 0.2
        },
        "num_neurons_pop": 10,
        "num_source_neurons": 10,
        "num_inhibitory_neurons": 10,
        "weight_inp": 0.011,
        "weight_self": 0.011,
        "weight_lat_inh": -0.009,
        "weight_lat_exc": 0.005,
        "prob_inp": 0.8,
        "prob_self": 0.8,
        "prob_lat_exc": 0.8,
        "firing_rate": 80,
        "delay": 1.0,
        "setup": {
            "timestep": 1.0
        }
    },
    "spikey": {
        "repeat": 10,
        "neuron_type": "IfFacetsHardware1",
        "neuron_params": {
            "tau_m": 6,
            "tau_refrac": 1,
            "v_rest": -70,
            "v_thresh": -55,
            "v_reset": -70,
            "e_rev_I": -80
        },
        "num_neurons_pop": 10,
        "num_source_neurons": 5,
        "num_inhibitory_neurons": 15,
        "weight_inp": 0.008,
        "weight_self": 0.004,
        "weight_lat_inh": -0.02,
        "weight_lat_exc": 0.002,
        "prob_inp": 0.8,
        "prob_self": 0.8,
        "prob_lat_exc": 0.8,
        "firing_rate": 30
    },
    "nmpm1": {
        "invalid": true,
        "setup": {
            "calib_path": "/wang/data/calibration/brainscales/default-2017-09-26-1",
            "neuron_size": 4,
            "digital_weight": true,
            "bandwidth": 0.8,
            "synapse_loss": true
        },
        "neuron_type": "IF_cond_exp",
        "neuron_params": {
            "e_rev_E": 30,
            "e_rev_I": -100,
            "v_rest": -60,
            "v_reset": -80,
            "v_thresh": -40,
            "tau_syn_E": 3,
            "tau_syn_I": 3,
            "tau_refrac": 1,
            "tau_m": 5,
            "cm": 0.2
        },
        "num_neurons_pop": 10,
        "num_source_neurons": 10,
        "num_inhibitory_neurons": 10,
        "weight_inp": 5,
        "weight_self": 10,
        "weight_lat_inh": -2,
        "weight_lat_exc": 2,
        "prob_inp": 0.2,
        "prob_self": 0.6,
        "prob_lat_exc": 0.7,
        "firing_rate": 60
    }
}